krls/__init__
krls/kernel.py
krls/krls.py
krls-0.0.4.dist-info/METADATA
krls-0.0.4.dist-info/WHEEL
krls-0.0.4.dist-info/licenses/LICENSE
krls-0.0.4.dist-info/RECORD
