Metadata-Version: 2.4
Name: krls
Version: 0.0.4
Summary: Kernel Recursive Least Square (KRLS)
Project-URL: Homepage, https://github.com/kaikerochaalves/KRLS_pypi.git
Project-URL: Issues, https://github.com/kaikerochaalves/KRLS_pypi.git
Author-email: Kaike Sa Teles Rocha Alves <kaikerochaalves@outlook.com>
License-File: LICENSE
Classifier: License :: OSI Approved :: GNU General Public License v3 (GPLv3)
Classifier: Programming Language :: Python :: 3
Requires-Python: >=3.0
Requires-Dist: numpy
Requires-Dist: torch
